imgyaso/__init__.py
imgyaso/__main__.py
imgyaso/adathres.py
imgyaso/dither.py
imgyaso/quant.py
imgyaso/trunc.py
imgyaso/util.py
imgyaso-2023.1.27.3.dist-info/LICENSE
imgyaso-2023.1.27.3.dist-info/METADATA
imgyaso-2023.1.27.3.dist-info/WHEEL
imgyaso-2023.1.27.3.dist-info/entry_points.txt
imgyaso-2023.1.27.3.dist-info/top_level.txt
imgyaso-2023.1.27.3.dist-info/RECORD
