Metadata-Version: 2.1
Name: imgyaso
Version: 2023.1.27.3
Summary: 提供多种图片有损压缩方式，包括自适应二值化、网格仿色、颜色缩减
Home-page: https://github.com/apachecn/imgyaso
Author: ApacheCN
Author-email: apachecn@163.com
License: UNKNOWN
Keywords: image,processing,lossy,compression,adaptive,threshold,bilevel,grid,dither,quantize,图像处理,有损压缩,自适应阈值,二值化,网格仿色,颜色缩减
Platform: UNKNOWN
Classifier: Development Status :: 4 - Beta
Classifier: Environment :: Console
Classifier: Intended Audience :: Developers
Classifier: Intended Audience :: End Users/Desktop
Classifier: License :: Other/Proprietary License
Classifier: Natural Language :: Chinese (Simplified)
Classifier: Natural Language :: English
Classifier: Operating System :: OS Independent
Classifier: Programming Language :: Python :: 3
Classifier: Programming Language :: Python :: 3 :: Only
Classifier: Programming Language :: Python :: 3.6
Classifier: Programming Language :: Python :: 3.7
Classifier: Topic :: Multimedia :: Graphics
Classifier: Topic :: Utilities
Requires-Python: >=3.6
Requires-Dist: numpy
Requires-Dist: scipy
Requires-Dist: opencv-python
Requires-Dist: pillow
Requires-Dist: libimagequant
